ze2nb/__init__.py
ze2nb/ze2nb.py
ze2nb-1.0.0.dist-info/LICENSE
ze2nb-1.0.0.dist-info/METADATA
ze2nb-1.0.0.dist-info/WHEEL
ze2nb-1.0.0.dist-info/top_level.txt
ze2nb-1.0.0.dist-info/RECORD
