Metadata-Version: 2.1
Name: ze2nb
Version: 1.0.0
Summary: Zeppelin to Jupyter Notebook 
Home-page: https://github.com/runawayhorse001/ze2nb.git
Author: Wenqiang Feng and Ryan Blue
Author-email: von198@gmail.com
License: MIT
Platform: UNKNOWN
Classifier: Development Status :: 2 - Pre-Alpha
Classifier: Framework :: IPython
Classifier: Framework :: Jupyter
Classifier: Environment :: Console
Classifier: Environment :: MacOS X
Classifier: Operating System :: MacOS
Classifier: License :: OSI Approved :: MIT License
Classifier: Intended Audience :: Developers
Classifier: Programming Language :: Python
Classifier: Programming Language :: Python :: 2
Classifier: Programming Language :: Python :: 3
Requires-Dist: ipython
Requires-Dist: nbformat
